{"fields": [0, 1, 2, 3, 4], "K": 3, "json": "{\"clusters\": [{\"stats\": [{\"anomalies\": [{\"value\": 5, \"label\": \"Iris-setosa\"}]}, {\"corrects\": [{\"value\": 21, \"label\": \"Iris-setosa\"}, {\"value\": 3, \"label\": \"Iris-versicolor\"}]}]}, {\"stats\": [{\"anomalies\": [{\"value\": 4, \"label\": \"Iris-setosa\"}]}, {\"corrects\": [{\"value\": 20, \"label\": \"Iris-setosa\"}]}]}, {\"stats\": [{\"anomalies\": [{\"value\": 19, \"label\": \"Iris-virginica\"}]}, {\"corrects\": [{\"value\": 47, \"label\": \"Iris-versicolor\"}, {\"value\": 31, \"label\": \"Iris-virginica\"}]}]}], \"N\": 20}", "file": "app/static/documents/iris.csv", "N": 20}